Metadata-Version: 2.1
Name: soda-core-athena
Version: 3.5.6
License-File: LICENSE
Requires-Dist: soda-core==3.5.6
Requires-Dist: PyAthena<3.0,>=2.2.0
